ct_redis/__init__.py
ct_redis/cache.py
ct_redis_sample-0.0.5.dist-info/METADATA
ct_redis_sample-0.0.5.dist-info/WHEEL
ct_redis_sample-0.0.5.dist-info/top_level.txt
ct_redis_sample-0.0.5.dist-info/RECORD
