Metadata-Version: 2.1
Name: ct-redis-sample
Version: 0.0.5
Summary: A specialized library developed by Credenti for efficient Redis caching in Flask applications.
Home-page: UNKNOWN
Author: credenti
License: UNKNOWN
Platform: UNKNOWN
Requires-Dist: redis (==5.2.0)
Requires-Dist: Flask (>=3.0.3)
